{"Train Iter (time)": 0.030094718933105467, "_timestamp": 1664320819.661108, "ETA (time)": 30010.483814811705, "Train Rays / Sec": 136164.2206736515, "Train Loss": 0.006255646701902151, "Train Loss Dict/rgb_loss": 0.006255646701902151, "Train Loss Dict/interlevel_loss": 0.0, "Train Loss Dict/distortion_loss": 0.0, "Train Metrics Dict/psnr": 22.037277221679688, "_runtime": 99.17119407653809, "_step": 2799, "Eval Loss": 0.009223050437867641, "Eval Loss Dict/rgb_loss": 0.009223050437867641, "Eval Loss Dict/interlevel_loss": 0.0, "Eval Loss Dict/distortion_loss": 0.0, "Eval Metrics Dict/psnr": 20.351253509521484, "Test Rays / Sec": 680629.6701884738, "Eval Images Metrics/psnr": 21.940139770507812, "Eval Images Metrics/ssim": 0.7050537467002869, "Eval Images Metrics/lpips": 0.2410268932580948, "Eval Images Metrics/image_idx": 16.0, "Eval Images Metrics/num_rays": 129600.0, "Eval Images/img": {"_type": "image-file", "sha256": "eea0aded7c631b46cfec67b384e290ae1a36a4e9c20c863685aa9465eb7f9077", "size": 368808, "path": "media/images/Eval Images/img_2500_eea0aded7c631b46cfec.png", "format": "png", "width": 960, "height": 270}, "Eval Images/accumulation": {"_type": "image-file", "sha256": "fb6d6eb0edb4e4dc445aebb745fd513773c2ba100af99bd297865f989b52e787", "size": 38669, "path": "media/images/Eval Images/accumulation_2500_fb6d6eb0edb4e4dc445a.png", "format": "png", "width": 480, "height": 270}, "Eval Images/depth": {"_type": "image-file", "sha256": "c9315e53a567e56090466ae47aa8a76716091fd1c9008bc4bda4f1948bfb8a48", "size": 67365, "path": "media/images/Eval Images/depth_2500_c9315e53a567e5609046.png", "format": "png", "width": 480, "height": 270}, "Eval Images/prop_depth_0": {"_type": "image-file", "sha256": "12897f6aa35976d49ad05f1f8fdc1203b9d2260e8fca0f70484be05bb56fcb82", "size": 288407, "path": "media/images/Eval Images/prop_depth_0_2500_12897f6aa35976d49ad0.png", "format": "png", "width": 480, "height": 270}, "Eval Images/prop_depth_1": {"_type": "image-file", "sha256": "dc64ff3adf0907ffd9e100af9fbdff4d3c055d62c48073ca881ab1edb1677328", "size": 300221, "path": "media/images/Eval Images/prop_depth_1_2500_dc64ff3adf0907ffd9e1.png", "format": "png", "width": 480, "height": 270}, "_wandb": {"runtime": 98}}