{"Train Iter (time)": 0.025441765785217285, "_timestamp": 1664343944.3820014, "ETA (time)": 25043.424058318138, "Train Rays / Sec": 161008.59216339752, "Train Loss": 0.002855131169781089, "Train Loss Dict/rgb_loss": 0.0023952287156134844, "Train Loss Dict/interlevel_loss": 0.00044718116987496614, "Train Loss Dict/distortion_loss": 1.2721161510853563e-05, "Train Metrics Dict/psnr": 26.206527709960938, "_runtime": 430.04202342033386, "_step": 15657, "Eval Loss": 0.005968891549855471, "Eval Loss Dict/rgb_loss": 0.005625068210065365, "Eval Loss Dict/interlevel_loss": 0.00033126608468592167, "Eval Loss Dict/distortion_loss": 1.2557364243548363e-05, "Eval Metrics Dict/psnr": 22.498722076416016, "Test Rays / Sec": 950070.0598405262, "Eval Images Metrics/psnr": 22.548053741455078, "Eval Images Metrics/ssim": 0.7928960919380188, "Eval Images Metrics/lpips": 0.1319342851638794, "Eval Images Metrics/image_idx": 19.0, "Eval Images Metrics/num_rays": 129600.0, "Eval Images/img": {"_type": "image-file", "sha256": "0668b3f54c4637a2a2dfd4c291216ba1a3b7ca91c0defdda93a9efa9333ce41b", "size": 473350, "path": "media/images/Eval Images/img_15500_0668b3f54c4637a2a2df.png", "format": "png", "width": 960, "height": 270}, "Eval Images/accumulation": {"_type": "image-file", "sha256": "fe7ddd1b58f5d7ab14039330e72c586b231eb0626c907ffd4e21ab769c7c3aa1", "size": 43249, "path": "media/images/Eval Images/accumulation_15500_fe7ddd1b58f5d7ab1403.png", "format": "png", "width": 480, "height": 270}, "Eval Images/depth": {"_type": "image-file", "sha256": "8ab3689a5da3992e989b2eea75ed4624fc2727f8cff9fa4af3ea00266f8884b6", "size": 66504, "path": "media/images/Eval Images/depth_15500_8ab3689a5da3992e989b.png", "format": "png", "width": 480, "height": 270}, "Eval Images/prop_depth_0": {"_type": "image-file", "sha256": "f5d5d5f357a246a7c937f603beb983196b6803b842b2a64cf07c22f97f0595e4", "size": 44921, "path": "media/images/Eval Images/prop_depth_0_15500_f5d5d5f357a246a7c937.png", "format": "png", "width": 480, "height": 270}, "Eval Images/prop_depth_1": {"_type": "image-file", "sha256": "eb32887cf43bd58089e721f6fada25aca0aad0fd0102c13cb766dde9d0dc4b93", "size": 64515, "path": "media/images/Eval Images/prop_depth_1_15500_eb32887cf43bd58089e7.png", "format": "png", "width": 480, "height": 270}, "_wandb": {"runtime": 429}}